[{"model": "main.navbar", "pk": 1, "fields": {"author": 2, "name": "Institut", "name_uz": "Institut", "name_ru": "институт", "name_en": "Institute", "parent": null, "visible": true, "status": "base", "order_num": 1, "inside_order_num": 0, "slug": "institut", "added_at": "2023-11-04T10:41:09.191Z", "update_user": null, "updated_at": "2023-11-04T10:41:09.191Z", "lft": 1, "rght": 20, "tree_id": 1, "level": 0}}, {"model": "main.navbar", "pk": 2, "fields": {"author": 2, "name": "Ta'lim", "name_uz": "Ta'lim", "name_ru": "Образование", "name_en": "Education", "parent": null, "visible": true, "status": "base", "order_num": 2, "inside_order_num": 0, "slug": "talim", "added_at": "2023-11-04T10:43:43.772Z", "update_user": null, "updated_at": "2023-11-04T10:43:43.772Z", "lft": 1, "rght": 16, "tree_id": 2, "level": 0}}, {"model": "main.navbar", "pk": 3, "fields": {"author": 2, "name": "Ilmiy-tadqiqot", "name_uz": "Ilmiy-tadqiqot", "name_ru": "Исследования", "name_en": "research", "parent": null, "visible": true, "status": "base", "order_num": 3, "inside_order_num": 0, "slug": "ilmiy-tadqiqot", "added_at": "2023-11-04T10:44:30.231Z", "update_user": null, "updated_at": "2023-11-04T10:44:30.231Z", "lft": 1, "rght": 24, "tree_id": 3, "level": 0}}, {"model": "main.navbar", "pk": 4, "fields": {"author": 2, "name": "Xalqaro aloqalar", "name_uz": "Xalqaro aloqalar", "name_ru": "Международные отношения", "name_en": "International relations", "parent": null, "visible": true, "status": "base", "order_num": 4, "inside_order_num": 0, "slug": "xalqaro-aloqalar", "added_at": "2023-11-04T10:45:01.538Z", "update_user": null, "updated_at": "2023-11-04T10:45:01.538Z", "lft": 1, "rght": 10, "tree_id": 4, "level": 0}}, {"model": "main.navbar", "pk": 5, "fields": {"author": 2, "name": "Talabalar", "name_uz": "Talabalar", "name_ru": "Студенты", "name_en": "Students", "parent": null, "visible": true, "status": "base", "order_num": 5, "inside_order_num": 0, "slug": "talabalar", "added_at": "2023-11-04T10:45:22.633Z", "update_user": null, "updated_at": "2023-11-04T10:45:22.633Z", "lft": 1, "rght": 24, "tree_id": 5, "level": 0}}, {"model": "main.navbar", "pk": 6, "fields": {"author": 2, "name": "Qabul", "name_uz": "Qabul", "name_ru": "Прием", "name_en": "Admission", "parent": null, "visible": true, "status": "base", "order_num": 6, "inside_order_num": 0, "slug": "qabul", "added_at": "2023-11-04T10:46:09.601Z", "update_user": 2, "updated_at": "2023-11-04T10:46:32.829Z", "lft": 1, "rght": 20, "tree_id": 6, "level": 0}}, {"model": "main.navbar", "pk": 7, "fields": {"author": 2, "name": "Biz haqimizda", "name_uz": "Biz haqimizda", "name_ru": "О нас", "name_en": "About us", "parent": 1, "visible": true, "status": "inside", "order_num": 0, "inside_order_num": 1, "slug": "biz-haqimizda", "added_at": "2023-11-04T10:47:16.272Z", "update_user": null, "updated_at": "2023-11-04T10:47:16.272Z", "lft": 2, "rght": 3, "tree_id": 1, "level": 1}}, {"model": "main.navbar", "pk": 8, "fields": {"author": 2, "name": "Rahbariyat", "name_uz": "Rahbariyat", "name_ru": "Структура", "name_en": "Structure", "parent": 1, "visible": true, "status": "inside", "order_num": 0, "inside_order_num": 2, "slug": "rahbariyat", "added_at": "2023-11-04T10:47:38.042Z", "update_user": null, "updated_at": "2023-11-04T10:47:38.042Z", "lft": 4, "rght": 5, "tree_id": 1, "level": 1}}, {"model": "main.navbar", "pk": 9, "fields": {"author": 2, "name": "Fakultet va kafedralar", "name_uz": "Fakultet va kafedralar", "name_ru": "Факультет и кафедры", "name_en": "Faculty and departments", "parent": 1, "visible": true, "status": "inside", "order_num": 0, "inside_order_num": 3, "slug": "fakultet-va-kafedralar", "added_at": "2023-11-04T10:48:17.422Z", "update_user": null, "updated_at": "2023-11-04T10:48:17.422Z", "lft": 6, "rght": 7, "tree_id": 1, "level": 1}}, {"model": "main.navbar", "pk": 10, "fields": {"author": 2, "name": "Bo’lim va markazlar", "name_uz": "Bo’lim va markazlar", "name_ru": "Отделения и центры", "name_en": "Department and centers", "parent": 1, "visible": true, "status": "inside", "order_num": 0, "inside_order_num": 4, "slug": "bolim-va-markazlar", "added_at": "2023-11-04T10:49:02.196Z", "update_user": null, "updated_at": "2023-11-04T10:49:02.196Z", "lft": 8, "rght": 9, "tree_id": 1, "level": 1}}, {"model": "main.navbar", "pk": 11, "fields": {"author": 2, "name": "BRM", "name_uz": "BRM", "name_ru": "ЦУР", "name_en": "SDG", "parent": 1, "visible": true, "status": "inside", "order_num": 0, "inside_order_num": 5, "slug": "brm", "added_at": "2023-11-04T10:49:25.509Z", "update_user": null, "updated_at": "2023-11-04T10:49:25.509Z", "lft": 10, "rght": 11, "tree_id": 1, "level": 1}}, {"model": "main.navbar", "pk": 12, "fields": {"author": 2, "name": "Institut hujjatlari", "name_uz": "Institut hujjatlari", "name_ru": "Документы о деятельности", "name_en": "Strategic Documents", "parent": 1, "visible": true, "status": "inside", "order_num": 0, "inside_order_num": 7, "slug": "institut-hujjatlari", "added_at": "2023-11-04T10:49:52.082Z", "update_user": null, "updated_at": "2023-11-04T10:49:52.082Z", "lft": 12, "rght": 13, "tree_id": 1, "level": 1}}, {"model": "main.navbar", "pk": 13, "fields": {"author": 2, "name": "Korrupsiyani oldini olish", "name_uz": "Korrupsiyani oldini olish", "name_ru": "Предотвращение", "name_en": "Prevent of corruption", "parent": 1, "visible": true, "status": "inside", "order_num": 0, "inside_order_num": 8, "slug": "korrupsiyani-oldini-olish", "added_at": "2023-11-04T10:50:09.769Z", "update_user": null, "updated_at": "2023-11-04T10:50:09.769Z", "lft": 14, "rght": 15, "tree_id": 1, "level": 1}}, {"model": "main.navbar", "pk": 14, "fields": {"author": 2, "name": "Bitiruvchilar", "name_uz": "Bitiruvchilar", "name_ru": "Выпускники", "name_en": "Alumni", "parent": 1, "visible": true, "status": "inside", "order_num": 0, "inside_order_num": 9, "slug": "bitiruvchilar", "added_at": "2023-11-04T10:50:31.249Z", "update_user": null, "updated_at": "2023-11-04T10:50:31.249Z", "lft": 16, "rght": 17, "tree_id": 1, "level": 1}}, {"model": "main.navbar", "pk": 15, "fields": {"author": 2, "name": "Filiallar", "name_uz": "Filiallar", "name_ru": "Филиалы", "name_en": "Branches", "parent": 1, "visible": true, "status": "inside", "order_num": 0, "inside_order_num": 10, "slug": "filiallar", "added_at": "2023-11-04T10:50:52.635Z", "update_user": null, "updated_at": "2023-11-04T10:50:52.635Z", "lft": 18, "rght": 19, "tree_id": 1, "level": 1}}, {"model": "main.navbar", "pk": 16, "fields": {"author": 2, "name": "Ilmiy kengash", "name_uz": "Ilmiy kengash", "name_ru": "Ученый совет", "name_en": "Scientific councils", "parent": 3, "visible": true, "status": "inside", "order_num": 0, "inside_order_num": 1, "slug": "ilmiy-kengash", "added_at": "2023-11-04T10:52:18.103Z", "update_user": null, "updated_at": "2023-11-04T10:52:18.103Z", "lft": 2, "rght": 3, "tree_id": 3, "level": 1}}, {"model": "main.navbar", "pk": 17, "fields": {"author": 2, "name": "Xalqaro loyiha", "name_uz": "Xalqaro loyiha", "name_ru": "Международный проект", "name_en": "International project", "parent": 3, "visible": true, "status": "inside", "order_num": 0, "inside_order_num": 4, "slug": "xalqaro-loyiha", "added_at": "2023-11-04T10:52:34.982Z", "update_user": 2, "updated_at": "2023-11-04T10:54:08.045Z", "lft": 8, "rght": 9, "tree_id": 3, "level": 1}}, {"model": "main.navbar", "pk": 18, "fields": {"author": 2, "name": "Ilmiy loyiha", "name_uz": "Ilmiy loyiha", "name_ru": "Научный проект", "name_en": "Scientific project", "parent": 3, "visible": true, "status": "inside", "order_num": 0, "inside_order_num": 2, "slug": "ilmiy-loyiha", "added_at": "2023-11-04T10:52:55.937Z", "update_user": null, "updated_at": "2023-11-04T10:52:55.937Z", "lft": 4, "rght": 5, "tree_id": 3, "level": 1}}, {"model": "main.navbar", "pk": 19, "fields": {"author": 2, "name": "Startup", "name_uz": "Startup", "name_ru": "Startup", "name_en": "Startup", "parent": 3, "visible": true, "status": "inside", "order_num": 0, "inside_order_num": 3, "slug": "startup", "added_at": "2023-11-04T10:53:09.354Z", "update_user": null, "updated_at": "2023-11-04T10:53:09.354Z", "lft": 6, "rght": 7, "tree_id": 3, "level": 1}}, {"model": "main.navbar", "pk": 20, "fields": {"author": 2, "name": "Xo’jalik shartnomalari", "name_uz": "Xo’jalik shartnomalari", "name_ru": "Контракты", "name_en": "Contracts", "parent": 3, "visible": true, "status": "inside", "order_num": 0, "inside_order_num": 5, "slug": "xojalik-shartnomalari", "added_at": "2023-11-04T10:53:36.724Z", "update_user": null, "updated_at": "2023-11-04T10:53:36.724Z", "lft": 10, "rght": 11, "tree_id": 3, "level": 1}}, {"model": "main.navbar", "pk": 21, "fields": {"author": 2, "name": "Ilmiy jurnal", "name_uz": "Ilmiy jurnal", "name_ru": "Научный журнал", "name_en": "Scientific journal", "parent": 3, "visible": true, "status": "inside", "order_num": 0, "inside_order_num": 6, "slug": "ilmiy-jurnal", "added_at": "2023-11-04T10:54:46.446Z", "update_user": null, "updated_at": "2023-11-04T10:54:46.446Z", "lft": 12, "rght": 13, "tree_id": 3, "level": 1}}, {"model": "main.navbar", "pk": 22, "fields": {"author": 2, "name": "Konferensiya", "name_uz": "Konferensiya", "name_ru": "Конференция", "name_en": "Conference", "parent": 3, "visible": true, "status": "inside", "order_num": 0, "inside_order_num": 7, "slug": "konferensiya", "added_at": "2023-11-04T10:55:04.642Z", "update_user": null, "updated_at": "2023-11-04T10:55:04.642Z", "lft": 14, "rght": 15, "tree_id": 3, "level": 1}}, {"model": "main.navbar", "pk": 23, "fields": {"author": 2, "name": "Ilmiy maktablar", "name_uz": "Ilmiy maktablar", "name_ru": "Научные школы", "name_en": "Scientific schools", "parent": 3, "visible": true, "status": "inside", "order_num": 0, "inside_order_num": 8, "slug": "ilmiy-maktablar", "added_at": "2023-11-04T10:55:30.387Z", "update_user": null, "updated_at": "2023-11-04T10:55:30.387Z", "lft": 16, "rght": 17, "tree_id": 3, "level": 1}}, {"model": "main.navbar", "pk": 24, "fields": {"author": 2, "name": "Ixtiro, EHM va boshqa dasturlar uchun guvohnomalar", "name_uz": "Ixtiro, EHM va boshqa dasturlar uchun guvohnomalar", "name_ru": "Получены патенты на изобретения, полезные модели, свидетельства на программы экспонирования", "name_en": "Obtained patents for inventions, utility models, certificates for exposure programs", "parent": 3, "visible": true, "status": "inside", "order_num": 0, "inside_order_num": 9, "slug": "ixtiro-ehm-va-boshqa-dasturlar-uchun-guvohnomalar", "added_at": "2023-11-04T10:55:58.723Z", "update_user": null, "updated_at": "2023-11-04T10:55:58.723Z", "lft": 18, "rght": 19, "tree_id": 3, "level": 1}}, {"model": "main.navbar", "pk": 25, "fields": {"author": 2, "name": "Doktorantura", "name_uz": "Doktorantura", "name_ru": "Докторантура", "name_en": "Doctorate", "parent": 3, "visible": true, "status": "inside", "order_num": 0, "inside_order_num": 10, "slug": "doktorantura", "added_at": "2023-11-04T10:56:16.281Z", "update_user": null, "updated_at": "2023-11-04T10:56:16.281Z", "lft": 20, "rght": 21, "tree_id": 3, "level": 1}}, {"model": "main.navbar", "pk": 26, "fields": {"author": 2, "name": "Avtoreferat", "name_uz": "Avtoreferat", "name_ru": "Автореферат", "name_en": "Abstract", "parent": 3, "visible": true, "status": "inside", "order_num": 0, "inside_order_num": 11, "slug": "avtoreferat", "added_at": "2023-11-04T10:56:36.875Z", "update_user": null, "updated_at": "2023-11-04T10:56:36.875Z", "lft": 22, "rght": 23, "tree_id": 3, "level": 1}}, {"model": "main.navbar", "pk": 27, "fields": {"author": 2, "name": "Xalqaro aloqalar bo’limi", "name_uz": "Xalqaro aloqalar bo’limi", "name_ru": "Департамент международных отношений", "name_en": "Department of International Relations", "parent": 4, "visible": true, "status": "inside", "order_num": 0, "inside_order_num": 1, "slug": "xalqaro-aloqalar-bolimi", "added_at": "2023-11-04T11:31:28.168Z", "update_user": null, "updated_at": "2023-11-04T11:31:28.168Z", "lft": 2, "rght": 3, "tree_id": 4, "level": 1}}, {"model": "main.navbar", "pk": 28, "fields": {"author": 2, "name": "Xalqaro grantlar", "name_uz": "Xalqaro grantlar", "name_ru": "Международные гранты", "name_en": "International grants", "parent": 4, "visible": true, "status": "inside", "order_num": 0, "inside_order_num": 2, "slug": "xalqaro-grantlar", "added_at": "2023-11-04T11:33:11.398Z", "update_user": null, "updated_at": "2023-11-04T11:33:11.398Z", "lft": 4, "rght": 5, "tree_id": 4, "level": 1}}, {"model": "main.navbar", "pk": 29, "fields": {"author": 2, "name": "Hamkor universitet va tashkilotlar", "name_uz": "Hamkor universitet va tashkilotlar", "name_ru": "Партнерские организации", "name_en": "Partner organizations", "parent": 4, "visible": true, "status": "inside", "order_num": 0, "inside_order_num": 3, "slug": "hamkor-universitet-va-tashkilotlar", "added_at": "2023-11-04T11:33:41.054Z", "update_user": null, "updated_at": "2023-11-04T11:33:41.054Z", "lft": 6, "rght": 7, "tree_id": 4, "level": 1}}, {"model": "main.navbar", "pk": 30, "fields": {"author": 2, "name": "Xalqaro faoliyat", "name_uz": "Xalqaro faoliyat", "name_ru": "международная деятельность", "name_en": "International activity", "parent": 4, "visible": true, "status": "inside", "order_num": 0, "inside_order_num": 4, "slug": "xalqaro-faoliyat", "added_at": "2023-11-04T11:33:59.598Z", "update_user": null, "updated_at": "2023-11-04T11:33:59.598Z", "lft": 8, "rght": 9, "tree_id": 4, "level": 1}}, {"model": "main.navbar", "pk": 31, "fields": {"author": 2, "name": "Moliya", "name_uz": "Moliya", "name_ru": "Финансы", "name_en": "Finance", "parent": 5, "visible": true, "status": "inside", "order_num": 0, "inside_order_num": 1, "slug": "moliya", "added_at": "2023-11-04T11:34:18.586Z", "update_user": null, "updated_at": "2023-11-04T11:34:18.586Z", "lft": 2, "rght": 3, "tree_id": 5, "level": 1}}, {"model": "main.navbar", "pk": 32, "fields": {"author": 2, "name": "Talabalar turar joyi", "name_uz": "Talabalar turar joyi", "name_ru": "Студенческая гостиница", "name_en": "Student accommodation", "parent": 5, "visible": true, "status": "inside", "order_num": 0, "inside_order_num": 2, "slug": "talabalar-turar-joyi", "added_at": "2023-11-04T11:34:41.520Z", "update_user": null, "updated_at": "2023-11-04T11:34:41.520Z", "lft": 4, "rght": 5, "tree_id": 5, "level": 1}}, {"model": "main.navbar", "pk": 33, "fields": {"author": 2, "name": "Tibbiyot bo’limi", "name_uz": "Tibbiyot bo’limi", "name_ru": "Медицинский отдел", "name_en": "Medical department", "parent": 5, "visible": true, "status": "inside", "order_num": 0, "inside_order_num": 3, "slug": "tibbiyot-bolimi", "added_at": "2023-11-04T11:35:02.405Z", "update_user": null, "updated_at": "2023-11-04T11:35:02.405Z", "lft": 6, "rght": 7, "tree_id": 5, "level": 1}}, {"model": "main.navbar", "pk": 34, "fields": {"author": 2, "name": "Iqtidorli talabalar", "name_uz": "Iqtidorli talabalar", "name_ru": "Талантливые студенты", "name_en": "Talented students", "parent": 5, "visible": true, "status": "inside", "order_num": 0, "inside_order_num": 4, "slug": "iqtidorli-talabalar", "added_at": "2023-11-04T11:35:27.588Z", "update_user": null, "updated_at": "2023-11-04T11:35:27.588Z", "lft": 8, "rght": 9, "tree_id": 5, "level": 1}}, {"model": "main.navbar", "pk": 35, "fields": {"author": 2, "name": "Sport", "name_uz": "Sport", "name_ru": "Спорт", "name_en": "Sports", "parent": 5, "visible": true, "status": "inside", "order_num": 0, "inside_order_num": 5, "slug": "sport", "added_at": "2023-11-04T11:35:47.266Z", "update_user": null, "updated_at": "2023-11-04T11:35:47.266Z", "lft": 10, "rght": 11, "tree_id": 5, "level": 1}}, {"model": "main.navbar", "pk": 36, "fields": {"author": 2, "name": "Ijtimoiy yordam", "name_uz": "Ijtimoiy yordam", "name_ru": "Социальная помощь", "name_en": "Social assistance", "parent": 5, "visible": true, "status": "inside", "order_num": 0, "inside_order_num": 6, "slug": "ijtimoiy-yordam", "added_at": "2023-11-04T11:36:13.743Z", "update_user": null, "updated_at": "2023-11-04T11:36:13.743Z", "lft": 12, "rght": 13, "tree_id": 5, "level": 1}}, {"model": "main.navbar", "pk": 37, "fields": {"author": 2, "name": "Tanlov va grandlar", "name_uz": "Tanlov va grandlar", "name_ru": "Соревнования и гранды", "name_en": "Competition and grands", "parent": 5, "visible": true, "status": "inside", "order_num": 0, "inside_order_num": 7, "slug": "tanlov-va-grandlar", "added_at": "2023-11-04T11:36:37.262Z", "update_user": null, "updated_at": "2023-11-04T11:36:37.262Z", "lft": 14, "rght": 15, "tree_id": 5, "level": 1}}, {"model": "main.navbar", "pk": 38, "fields": {"author": 2, "name": "Startup loyihalar", "name_uz": "Startup loyihalar", "name_ru": "Стартап проекты", "name_en": "Startup projects", "parent": 5, "visible": true, "status": "inside", "order_num": 0, "inside_order_num": 8, "slug": "startup-loyihalar", "added_at": "2023-11-04T11:36:55.451Z", "update_user": null, "updated_at": "2023-11-04T11:36:55.451Z", "lft": 16, "rght": 17, "tree_id": 5, "level": 1}}, {"model": "main.navbar", "pk": 39, "fields": {"author": 2, "name": "Talabalarni baholash", "name_uz": "Talabalarni baholash", "name_ru": "оценка учащихся", "name_en": "Student assessment", "parent": 5, "visible": true, "status": "inside", "order_num": 0, "inside_order_num": 9, "slug": "talabalarni-baholash", "added_at": "2023-11-04T11:37:16.513Z", "update_user": null, "updated_at": "2023-11-04T11:37:16.513Z", "lft": 18, "rght": 19, "tree_id": 5, "level": 1}}, {"model": "main.navbar", "pk": 40, "fields": {"author": 2, "name": "Bo’sh ish o’rinlari", "name_uz": "Bo’sh ish o’rinlari", "name_ru": "Вакансии", "name_en": "Vacancies", "parent": 5, "visible": true, "status": "inside", "order_num": 0, "inside_order_num": 10, "slug": "bosh-ish-orinlari", "added_at": "2023-11-04T11:37:40.704Z", "update_user": null, "updated_at": "2023-11-04T11:37:40.704Z", "lft": 20, "rght": 21, "tree_id": 5, "level": 1}}, {"model": "main.navbar", "pk": 41, "fields": {"author": 2, "name": "Ma’naviyat", "name_uz": "Ma’naviyat", "name_ru": "Духовность", "name_en": "Spirituality", "parent": 5, "visible": true, "status": "inside", "order_num": 0, "inside_order_num": 11, "slug": "manaviyat", "added_at": "2023-11-04T11:38:03.823Z", "update_user": null, "updated_at": "2023-11-04T11:38:03.823Z", "lft": 22, "rght": 23, "tree_id": 5, "level": 1}}, {"model": "main.navbar", "pk": 42, "fields": {"author": 2, "name": "Ikkinchi mutaxassislik", "name_uz": "Ikkinchi mutaxassislik", "name_ru": "Вторая специальность", "name_en": "Second specialty", "parent": 2, "visible": true, "status": "inside", "order_num": 0, "inside_order_num": 1, "slug": "ikkinchi-mutaxassislik", "added_at": "2023-11-04T11:39:00.240Z", "update_user": null, "updated_at": "2023-11-04T11:39:00.240Z", "lft": 2, "rght": 3, "tree_id": 2, "level": 1}}, {"model": "main.navbar", "pk": 43, "fields": {"author": 2, "name": "Sirtqi ta’lim", "name_uz": "Sirtqi ta’lim", "name_ru": "Внешнее образование", "name_en": "External education", "parent": 2, "visible": true, "status": "inside", "order_num": 0, "inside_order_num": 2, "slug": "sirtqi-talim", "added_at": "2023-11-04T11:39:41.543Z", "update_user": null, "updated_at": "2023-11-04T11:39:41.543Z", "lft": 4, "rght": 5, "tree_id": 2, "level": 1}}, {"model": "main.navbar", "pk": 44, "fields": {"author": 2, "name": "Qo’shma ta’lim", "name_uz": "Qo’shma ta’lim", "name_ru": "Совместное обучение", "name_en": "Joint education", "parent": 2, "visible": true, "status": "inside", "order_num": 0, "inside_order_num": 3, "slug": "qoshma-talim", "added_at": "2023-11-04T11:40:21.842Z", "update_user": null, "updated_at": "2023-11-04T11:40:21.842Z", "lft": 6, "rght": 7, "tree_id": 2, "level": 1}}, {"model": "main.navbar", "pk": 45, "fields": {"author": 2, "name": "Magistratura", "name_uz": "Magistratura", "name_ru": "Магистратура", "name_en": "Magistracy", "parent": 2, "visible": true, "status": "inside", "order_num": 0, "inside_order_num": 4, "slug": "magistratura", "added_at": "2023-11-04T11:41:44.875Z", "update_user": null, "updated_at": "2023-11-04T11:41:44.875Z", "lft": 8, "rght": 9, "tree_id": 2, "level": 1}}, {"model": "main.navbar", "pk": 46, "fields": {"author": 2, "name": "Bakalavriyat", "name_uz": "Bakalavriyat", "name_ru": "Бакалавриат", "name_en": "Bachelor's degree", "parent": 2, "visible": true, "status": "inside", "order_num": 0, "inside_order_num": 5, "slug": "bakalavriyat", "added_at": "2023-11-04T11:42:30.359Z", "update_user": null, "updated_at": "2023-11-04T11:42:30.359Z", "lft": 10, "rght": 11, "tree_id": 2, "level": 1}}, {"model": "main.navbar", "pk": 47, "fields": {"author": 2, "name": "Malakaviy talablar", "name_uz": "Malakaviy talablar", "name_ru": "Квалификационные требования", "name_en": "Qualification requirements", "parent": 2, "visible": true, "status": "inside", "order_num": 0, "inside_order_num": 6, "slug": "malakaviy-talablar", "added_at": "2023-11-04T11:43:37.850Z", "update_user": null, "updated_at": "2023-11-04T11:43:37.850Z", "lft": 12, "rght": 13, "tree_id": 2, "level": 1}}, {"model": "main.navbar", "pk": 48, "fields": {"author": 2, "name": "Oʻquv reja", "name_uz": "Oʻquv reja", "name_ru": "Учебный план", "name_en": "curriculum", "parent": 2, "visible": true, "status": "inside", "order_num": 0, "inside_order_num": 7, "slug": "oquv-reja", "added_at": "2023-11-04T11:45:47.956Z", "update_user": null, "updated_at": "2023-11-04T11:45:47.956Z", "lft": 14, "rght": 15, "tree_id": 2, "level": 1}}, {"model": "main.navbar", "pk": 49, "fields": {"author": 2, "name": "Magistratura", "name_uz": "Magistratura", "name_ru": "Магистратура", "name_en": "Magistracy", "parent": 6, "visible": true, "status": "inside", "order_num": 0, "inside_order_num": 1, "slug": "magistratura-qabul", "added_at": "2023-11-04T11:51:25.513Z", "update_user": null, "updated_at": "2023-11-04T11:51:25.513Z", "lft": 2, "rght": 3, "tree_id": 6, "level": 1}}, {"model": "main.navbar", "pk": 50, "fields": {"author": 2, "name": "Bakalavr", "name_uz": "Bakalavr", "name_ru": "Бакалавр", "name_en": "Bachelor", "parent": 6, "visible": true, "status": "inside", "order_num": 0, "inside_order_num": 2, "slug": "bakalavr", "added_at": "2023-11-04T11:52:10.962Z", "update_user": null, "updated_at": "2023-11-04T11:52:10.962Z", "lft": 4, "rght": 5, "tree_id": 6, "level": 1}}, {"model": "main.navbar", "pk": 51, "fields": {"author": 2, "name": "Doktorantura", "name_uz": "Doktorantura", "name_ru": "Докторантура", "name_en": "Doctorantura", "parent": 6, "visible": true, "status": "inside", "order_num": 0, "inside_order_num": 3, "slug": "doktorantura-qabul", "added_at": "2023-11-04T11:52:55.594Z", "update_user": null, "updated_at": "2023-11-04T11:52:55.594Z", "lft": 6, "rght": 7, "tree_id": 6, "level": 1}}, {"model": "main.navbar", "pk": 52, "fields": {"author": 2, "name": "Qo’shma ta’lim", "name_uz": "Qo’shma ta’lim", "name_ru": "Совместное обучение", "name_en": "Joint education", "parent": 6, "visible": true, "status": "inside", "order_num": 0, "inside_order_num": 3, "slug": "qoshma-talim-qabul", "added_at": "2023-11-04T11:53:40.039Z", "update_user": null, "updated_at": "2023-11-04T11:53:40.039Z", "lft": 8, "rght": 9, "tree_id": 6, "level": 1}}, {"model": "main.navbar", "pk": 53, "fields": {"author": 2, "name": "O’qishni ko’chirish va qayta tiklash", "name_uz": "O’qishni ko’chirish va qayta tiklash", "name_ru": "Перенос и восстановление учебы", "name_en": "Transfer and recovery of studies", "parent": 6, "visible": true, "status": "inside", "order_num": 0, "inside_order_num": 5, "slug": "oqishni-kochirish-va-qayta-tiklash", "added_at": "2023-11-04T11:54:43.119Z", "update_user": null, "updated_at": "2023-11-04T11:54:43.119Z", "lft": 10, "rght": 11, "tree_id": 6, "level": 1}}, {"model": "main.navbar", "pk": 54, "fields": {"author": 2, "name": "Ikkinchi oliy ta'lim (2-mutaxasislik)", "name_uz": "Ikkinchi oliy ta'lim (2-mutaxasislik)", "name_ru": "Второе высшее образование (2-я специальность)", "name_en": "Second higher education (2nd specialty)", "parent": 6, "visible": true, "status": "inside", "order_num": 0, "inside_order_num": 6, "slug": "ikkinchi-oliy-talim-2-mutaxasislik", "added_at": "2023-11-04T11:55:12.047Z", "update_user": null, "updated_at": "2023-11-04T11:55:12.047Z", "lft": 12, "rght": 13, "tree_id": 6, "level": 1}}, {"model": "main.navbar", "pk": 55, "fields": {"author": 2, "name": "Qabul - xorijiy abiturientlar uchun", "name_uz": "Qabul - xorijiy abiturientlar uchun", "name_ru": "Прием - для иностранных абитуриентов", "name_en": "Admission - for foreign applicants", "parent": 6, "visible": true, "status": "inside", "order_num": 0, "inside_order_num": 7, "slug": "qabul-xorijiy-abiturientlar-uchun", "added_at": "2023-11-04T11:55:52.944Z", "update_user": null, "updated_at": "2023-11-04T11:55:52.944Z", "lft": 14, "rght": 15, "tree_id": 6, "level": 1}}, {"model": "main.navbar", "pk": 56, "fields": {"author": 2, "name": "Texnikum bitiruvchilarini qabul qilish", "name_uz": "Texnikum bitiruvchilarini qabul qilish", "name_ru": "Прием выпускников техникума", "name_en": "Admission of technical school graduates", "parent": 6, "visible": true, "status": "inside", "order_num": 0, "inside_order_num": 8, "slug": "texnikum-bitiruvchilarini-qabul-qilish", "added_at": "2023-11-04T11:56:24.815Z", "update_user": null, "updated_at": "2023-11-04T11:56:24.815Z", "lft": 16, "rght": 17, "tree_id": 6, "level": 1}}, {"model": "main.navbar", "pk": 57, "fields": {"author": 2, "name": "Qabul natijalari", "name_uz": "Qabul natijalari", "name_ru": "Результаты поступления", "name_en": "Admission results", "parent": 6, "visible": true, "status": "inside", "order_num": 0, "inside_order_num": 9, "slug": "qabul-natijalari", "added_at": "2023-11-04T11:56:53.193Z", "update_user": null, "updated_at": "2023-11-04T11:56:53.193Z", "lft": 18, "rght": 19, "tree_id": 6, "level": 1}}]